{
  "indexes": [
    {
      "collectionGroup": "clients",
      "queryScope": "COLLECTION",
      "fields": [
        {
          "fieldPath": "status",
          "order": "ASCENDING"
        },
        {
          "fieldPath": "registrationDate",
          "order": "DESCENDING"
        }
      ]
    },
    {
      "collectionGroup": "consultations",
      "queryScope": "COLLECTION",
      "fields": [
        {
          "fieldPath": "source",
          "order": "ASCENDING"
        },
        {
          "fieldPath": "createdAt",
          "order": "DESCENDING"
        }
      ]
    },
    {
      "collectionGroup": "consultations",
      "queryScope": "COLLECTION",
      "fields": [
        {
          "fieldPath": "status",
          "order": "ASCENDING"
        },
        {
          "fieldPath": "createdAt",
          "order": "DESCENDING"
        }
      ]
    },
    {
      "collectionGroup": "consultations",
      "queryScope": "COLLECTION",
      "fields": [
        {
          "fieldPath": "priority",
          "order": "ASCENDING"
        },
        {
          "fieldPath": "createdAt",
          "order": "DESCENDING"
        }
      ]
    },
    {
      "collectionGroup": "consultations",
      "queryScope": "COLLECTION",
      "fields": [
        {
          "fieldPath": "clientEmail",
          "order": "ASCENDING"
        },
        {
          "fieldPath": "createdAt",
          "order": "DESCENDING"
        }
      ]
    },
    {
      "collectionGroup": "appointments",
      "queryScope": "COLLECTION",
      "fields": [
        {
          "fieldPath": "planType",
          "order": "ASCENDING"
        },
        {
          "fieldPath": "date",
          "order": "DESCENDING"
        },
        {
          "fieldPath": "time",
          "order": "DESCENDING"
        }
      ]
    },
    {
      "collectionGroup": "appointments",
      "queryScope": "COLLECTION",
      "fields": [
        {
          "fieldPath": "status",
          "order": "ASCENDING"
        },
        {
          "fieldPath": "date",
          "order": "DESCENDING"
        },
        {
          "fieldPath": "time",
          "order": "DESCENDING"
        }
      ]
    },
    {
      "collectionGroup": "appointments",
      "queryScope": "COLLECTION",
      "fields": [
        {
          "fieldPath": "date",
          "order": "ASCENDING"
        },
        {
          "fieldPath": "time",
          "order": "ASCENDING"
        }
      ]
    },
    {
      "collectionGroup": "appointments",
      "queryScope": "COLLECTION",
      "fields": [
        {
          "fieldPath": "date",
          "order": "DESCENDING"
        },
        {
          "fieldPath": "time",
          "order": "DESCENDING"
        }
      ]
    },
    {
      "collectionGroup": "appointments",
      "queryScope": "COLLECTION",
      "fields": [
        {
          "fieldPath": "clientId",
          "order": "ASCENDING"
        },
        {
          "fieldPath": "date",
          "order": "DESCENDING"
        },
        {
          "fieldPath": "time",
          "order": "DESCENDING"
        }
      ]
    },
    {
      "collectionGroup": "appointments",
      "queryScope": "COLLECTION",
      "fields": [
        {
          "fieldPath": "clientEmail",
          "order": "ASCENDING"
        },
        {
          "fieldPath": "selectedDate",
          "order": "DESCENDING"
        }
      ]
    }
  ],
  "fieldOverrides": []
}